{
  "project_info": {
    "project_number": "321718599292",
    "project_id": "suppa-229ad",
    "storage_bucket": "suppa-229ad.appspot.com"
  },
  "client": [
    {
      "client_info": {
        "mobilesdk_app_id": "1:321718599292:android:af1f678012f175a560d3f9",
        "android_client_info": {
          "package_name": "com.example.shop_app"
        }
      },
      "oauth_client": [
        {
          "client_id": "321718599292-i0um308f34nvifan9br46u673sjdkkk2.apps.googleusercontent.com",
          "client_type": 3
        }
      ],
      "api_key": [
        {
          "current_key": "AIzaSyBJe7GJhqxVEKBuIE9u60wvrRJvnkm1BXc"
        }
      ],
      "services": {
        "appinvite_service": {
          "other_platform_oauth_client": [
            {
              "client_id": "321718599292-i0um308f34nvifan9br46u673sjdkkk2.apps.googleusercontent.com",
              "client_type": 3
            }
          ]
        }
      }
    }
  ],
  "configuration_version": "1"
}